msk_seg_util/__init__.py
msk_seg_util/paired_scan.py
msk_seg_util/util/__init__.py
msk_seg_util/util/io_util.py
msk_seg_util/util/metric_util.py
msk_seg_util/util/plt_util.py
msk_seg_util/util/stats_util.py
msk_seg_util/util/vis_util.py
tests/__init__.py
tests/util/__init__.py
tests/util/test_metric_util.py
msk_seg_util-0.0.2.dist-info/LICENSE
msk_seg_util-0.0.2.dist-info/METADATA
msk_seg_util-0.0.2.dist-info/WHEEL
msk_seg_util-0.0.2.dist-info/top_level.txt
msk_seg_util-0.0.2.dist-info/RECORD
