Metadata-Version: 2.1
Name: msk-seg-util
Version: 0.0.2
Summary: Python package for MSK segmentation utilities
Home-page: https://github.com/ad12/msk_seg_util
Author: Arjun Desai
Author-email: arjundd@stanford.edu
License: MIT
Platform: UNKNOWN
Classifier: Programming Language :: Python :: 3
Classifier: Operating System :: OS Independent
Requires-Python: >=3.6
Requires-Dist: h5py
Requires-Dist: matplotlib
Requires-Dist: medpy
Requires-Dist: numpy
Requires-Dist: opencv-python
Requires-Dist: pandas
Requires-Dist: pyvisstats
Requires-Dist: scipy
Requires-Dist: seaborn
